{
  "selections": {
    "mode": "SIMPLE"
  },
  "placements": {},
  "schematic_projects_manager": {},
  "operation_mode": "AREA_SELECTION",
  "render_range": {
    "mode": "ALL",
    "axis": "y",
    "layer_single": 0,
    "layer_above": 0,
    "layer_below": 0,
    "layer_range_min": 0,
    "layer_range_max": 0,
    "hotkey_range_min": false,
    "hotkey_range_max": false
  },
  "area_simple": {
    "name": "airport-terminals-3and4",
    "current": "airport-terminals-3and4",
    "boxes": [
      {
        "pos1": [
          1391,
          68,
          -4049
        ],
        "pos2": [
          1420,
          80,
          -3952
        ],
        "name": "airport-terminals-3and4"
      }
    ]
  },
  "tool_mode_data": {
    "delete": {
      "use_placement": false
    }
  }
}